Metadata-Version: 2.2
Name: notramp
Version: 1.1.9
Summary: Super-fast Normalization and Trimming for Amplicon Sequencing Data (Long- and Short-read)
Home-page: https://github.com/simakro/NoTrAmp.git
Author: Simon Magin
Author-email: simon.magin@uk-essen.de
License: BSD-2
Classifier: Programming Language :: Python :: 3
Classifier: Operating System :: OS Independent
Requires-Python: >=3.7
License-File: LICENSE
Requires-Dist: psutil
Dynamic: author
Dynamic: author-email
Dynamic: classifier
Dynamic: description
Dynamic: description-content-type
Dynamic: home-page
Dynamic: license
Dynamic: requires-dist
Dynamic: requires-python
Dynamic: summary
